glsitevcl-1.0.3.data/purelib/glsitevcl/__init__.py
glsitevcl-1.0.3.data/purelib/glsitevcl/__version__.py
glsitevcl-1.0.3.data/purelib/glsitevcl/Win32/glsitevcl.pyd
glsitevcl-1.0.3.data/purelib/glsitevcl/Win64/glsitevcl.pyd
glsitevcl-1.0.3.dist-info/LICENSE.md
glsitevcl-1.0.3.dist-info/METADATA
glsitevcl-1.0.3.dist-info/WHEEL
glsitevcl-1.0.3.dist-info/top_level.txt
glsitevcl-1.0.3.dist-info/RECORD
